aspyx_persistence/__init__.py
aspyx_persistence/persistent_unit.py
aspyx_persistence/relation_synchronizer.py
aspyx_persistence/repository.py
aspyx_persistence/transactional.py
aspyx_persistence-0.1.6.dist-info/METADATA
aspyx_persistence-0.1.6.dist-info/WHEEL
aspyx_persistence-0.1.6.dist-info/licenses/LICENSE
aspyx_persistence-0.1.6.dist-info/RECORD
