Metadata-Version: 2.4
Name: aspyx_persistence
Version: 0.1.6
Summary: Aspyx persistence framework
Author-email: Andreas Ernst <andreas.ernst7@gmail.com>
License: MIT License
License-File: LICENSE
Requires-Python: >=3.9
Requires-Dist: aspyx>=1.9.5
Requires-Dist: sqlalchemy>=2.0.41
